bus_burgos/__init__.py
bus_burgos-0.1.2.dist-info/METADATA
bus_burgos-0.1.2.dist-info/WHEEL
bus_burgos-0.1.2.dist-info/RECORD
